Workbook

Sheet Портфейл
B2: 💰 P&L ТРЕКЕР — Колко си спечелил / загубил?
B3: Обновено (бот): | D3: =IF(COUNTA(Live!$A:$A)>1,INDEX(Live!$M:$M,2),INDEX(Данни!$M:$M,2)) -> 2026-09-27T14:34+03:00 | G3: =IF(COUNTA(Live!$A:$A)>1,"● Live данни от GitHub","● Снимка (Live не е свързан — виж Настройка)") -> ● Снимка (Live не е свързан — виж Настройка)
B5: Група | C5: Актив | D5: ID | E5: Вложено (€) | F5: Текуща стойност (€) | G5: Печалба/Загуба (€) | H5: Доходност (%) | I5: Статус | J5: Цена | K5: Вал. | L5: Дн. промяна
B6: Investments | C6: iShares ETF (EXI2) | D6: EXI2 | E6: =IFERROR(INDEX(Live!$I:$I,MATCH($D6,Live!$A:$A,0)),INDEX(Данни!$I:$I,MATCH($D6,Данни!$A:$A,0))) -> 50 | F6: =IFERROR(INDEX(Live!$H:$H,MATCH($D6,Live!$A:$A,0)),INDEX(Данни!$H:$H,MATCH($D6,Данни!$A:$A,0))) -> 56.2 | G6: =F6-E6 -> 6.2 | H6: =IF(E6=0,0,G6/E6) -> 0.124 | I6: =IF(H6>=0.5,"🚀 Отлично!",IF(H6>=0.2,"✅ Добре",IF(H6>=0,"📈 На плюс",IF(H6>=-0.15,"😐 Малка загуба — задръж",IF(H6>=-0.3,"⚠️ Внимание","🚨 Под -30% — прегледай стратегия"))))) -> 📈 На плюс | J6: =IFERROR(INDEX(Live!$D:$D,MATCH($D6,Live!$A:$A,0)),INDEX(Данни!$D:$D,MATCH($D6,Данни!$A:$A,0))) -> 117.70528 | K6: =IFERROR(INDEX(Live!$E:$E,MATCH($D6,Live!$A:$A,0)),INDEX(Данни!$E:$E,MATCH($D6,Данни!$A:$A,0))) -> EUR | L6: =IFERROR(IFERROR(INDEX(Live!$L:$L,MATCH($D6,Live!$A:$A,0)),INDEX(Данни!$L:$L,MATCH($D6,Данни!$A:$A,0)))/100,0) -> 0
C7: Marvell | D7: MRVL | E7: =IFERROR(INDEX(Live!$I:$I,MATCH($D7,Live!$A:$A,0)),INDEX(Данни!$I:$I,MATCH($D7,Данни!$A:$A,0))) -> 37.04 | F7: =IFERROR(INDEX(Live!$H:$H,MATCH($D7,Live!$A:$A,0)),INDEX(Данни!$H:$H,MATCH($D7,Данни!$A:$A,0))) -> 59.46 | G7: =F7-E7 -> 22.42 | H7: =IF(E7=0,0,G7/E7) -> 0.60529158 | I7: =IF(H7>=0.5,"🚀 Отлично!",IF(H7>=0.2,"✅ Добре",IF(H7>=0,"📈 На плюс",IF(H7>=-0.15,"😐 Малка загуба — задръж",IF(H7>=-0.3,"⚠️ Внимание","🚨 Под -30% — прегледай стратегия"))))) -> 🚀 Отлично! | J7: =IFERROR(INDEX(Live!$D:$D,MATCH($D7,Live!$A:$A,0)),INDEX(Данни!$D:$D,MATCH($D7,Данни!$A:$A,0))) -> 261.77738 | K7: =IFERROR(INDEX(Live!$E:$E,MATCH($D7,Live!$A:$A,0)),INDEX(Данни!$E:$E,MATCH($D7,Данни!$A:$A,0))) -> USD | L7: =IFERROR(IFERROR(INDEX(Live!$L:$L,MATCH($D7,Live!$A:$A,0)),INDEX(Данни!$L:$L,MATCH($D7,Данни!$A:$A,0)))/100,0) -> 0
C8: VanEck Defense ETF | D8: DFEN | E8: =IFERROR(INDEX(Live!$I:$I,MATCH($D8,Live!$A:$A,0)),INDEX(Данни!$I:$I,MATCH($D8,Данни!$A:$A,0))) -> 49 | F8: =IFERROR(INDEX(Live!$H:$H,MATCH($D8,Live!$A:$A,0)),INDEX(Данни!$H:$H,MATCH($D8,Данни!$A:$A,0))) -> 45.54 | G8: =F8-E8 -> -3.46 | H8: =IF(E8=0,0,G8/E8) -> -0.070612245 | I8: =IF(H8>=0.5,"🚀 Отлично!",IF(H8>=0.2,"✅ Добре",IF(H8>=0,"📈 На плюс",IF(H8>=-0.15,"😐 Малка загуба — задръж",IF(H8>=-0.3,"⚠️ Внимание","🚨 Под -30% — прегледай стратегия"))))) -> 😐 Малка загуба — задръж | J8: =IFERROR(INDEX(Live!$D:$D,MATCH($D8,Live!$A:$A,0)),INDEX(Данни!$D:$D,MATCH($D8,Данни!$A:$A,0))) -> 52.138653 | K8: =IFERROR(INDEX(Live!$E:$E,MATCH($D8,Live!$A:$A,0)),INDEX(Данни!$E:$E,MATCH($D8,Данни!$A:$A,0))) -> EUR | L8: =IFERROR(IFERROR(INDEX(Live!$L:$L,MATCH($D8,Live!$A:$A,0)),INDEX(Данни!$L:$L,MATCH($D8,Данни!$A:$A,0)))/100,0) -> 0
C9: NVIDIA | D9: NVDA | E9: =IFERROR(INDEX(Live!$I:$I,MATCH($D9,Live!$A:$A,0)),INDEX(Данни!$I:$I,MATCH($D9,Данни!$A:$A,0))) -> 74.08 | F9: =IFERROR(INDEX(Live!$H:$H,MATCH($D9,Live!$A:$A,0)),INDEX(Данни!$H:$H,MATCH($D9,Данни!$A:$A,0))) -> 69.32 | G9: =F9-E9 -> -4.76 | H9: =IF(E9=0,0,G9/E9) -> -0.06425486 | I9: =IF(H9>=0.5,"🚀 Отлично!",IF(H9>=0.2,"✅ Добре",IF(H9>=0,"📈 На плюс",IF(H9>=-0.15,"😐 Малка загуба — задръж",IF(H9>=-0.3,"⚠️ Внимание","🚨 Под -30% — прегледай стратегия"))))) -> 😐 Малка загуба — задръж | J9: =IFERROR(INDEX(Live!$D:$D,MATCH($D9,Live!$A:$A,0)),INDEX(Данни!$D:$D,MATCH($D9,Данни!$A:$A,0))) -> 224.33783 | K9: =IFERROR(INDEX(Live!$E:$E,MATCH($D9,Live!$A:$A,0)),INDEX(Данни!$E:$E,MATCH($D9,Данни!$A:$A,0))) -> USD | L9: =IFERROR(IFERROR(INDEX(Live!$L:$L,MATCH($D9,Live!$A:$A,0)),INDEX(Данни!$L:$L,MATCH($D9,Данни!$A:$A,0)))/100,0) -> 0
C10: Robo-Advisor | D10: ROBO | E10: =IFERROR(INDEX(Live!$I:$I,MATCH($D10,Live!$A:$A,0)),INDEX(Данни!$I:$I,MATCH($D10,Данни!$A:$A,0))) -> 23.42 | F10: =IFERROR(INDEX(Live!$H:$H,MATCH($D10,Live!$A:$A,0)),INDEX(Данни!$H:$H,MATCH($D10,Данни!$A:$A,0))) -> 20.81 | G10: =F10-E10 -> -2.61 | H10: =IF(E10=0,0,G10/E10) -> -0.11144321 | I10: =IF(H10>=0.5,"🚀 Отлично!",IF(H10>=0.2,"✅ Добре",IF(H10>=0,"📈 На плюс",IF(H10>=-0.15,"😐 Малка загуба — задръж",IF(H10>=-0.3,"⚠️ Внимание","🚨 Под -30% — прегледай стратегия"))))) -> 😐 Малка загуба — задръж | J10: =IFERROR(INDEX(Live!$D:$D,MATCH($D10,Live!$A:$A,0)),INDEX(Данни!$D:$D,MATCH($D10,Данни!$A:$A,0))) -> 20.81 | K10: =IFERROR(INDEX(Live!$E:$E,MATCH($D10,Live!$A:$A,0)),INDEX(Данни!$E:$E,MATCH($D10,Данни!$A:$A,0))) -> EUR | L10: =IFERROR(IFERROR(INDEX(Live!$L:$L,MATCH($D10,Live!$A:$A,0)),INDEX(Данни!$L:$L,MATCH($D10,Данни!$A:$A,0)))/100,0) -> 0
B11: CRYPTO | C11: Bitcoin | D11: BTC | E11: =IFERROR(INDEX(Live!$I:$I,MATCH($D11,Live!$A:$A,0)),INDEX(Данни!$I:$I,MATCH($D11,Данни!$A:$A,0))) -> 107 | F11: =IFERROR(INDEX(Live!$H:$H,MATCH($D11,Live!$A:$A,0)),INDEX(Данни!$H:$H,MATCH($D11,Данни!$A:$A,0))) -> 120.74 | G11: =F11-E11 -> 13.74 | H11: =IF(E11=0,0,G11/E11) -> 0.12841121 | I11: =IF(H11>=0.5,"🚀 Отлично!",IF(H11>=0.2,"✅ Добре",IF(H11>=0,"📈 На плюс",IF(H11>=-0.15,"😐 Малка загуба — задръж",IF(H11>=-0.3,"⚠️ Внимание","🚨 Под -30% — прегледай стратегия"))))) -> 📈 На плюс | J11: =IFERROR(INDEX(Live!$D:$D,MATCH($D11,Live!$A:$A,0)),INDEX(Данни!$D:$D,MATCH($D11,Данни!$A:$A,0))) -> 84835.06 | K11: =IFERROR(INDEX(Live!$E:$E,MATCH($D11,Live!$A:$A,0)),INDEX(Данни!$E:$E,MATCH($D11,Данни!$A:$A,0))) -> USD | L11: =IFERROR(IFERROR(INDEX(Live!$L:$L,MATCH($D11,Live!$A:$A,0)),INDEX(Данни!$L:$L,MATCH($D11,Данни!$A:$A,0)))/100,0) -> 0
C12: Ethereum Classic | D12: ETC | E12: =IFERROR(INDEX(Live!$I:$I,MATCH($D12,Live!$A:$A,0)),INDEX(Данни!$I:$I,MATCH($D12,Данни!$A:$A,0))) -> 58.03 | F12: =IFERROR(INDEX(Live!$H:$H,MATCH($D12,Live!$A:$A,0)),INDEX(Данни!$H:$H,MATCH($D12,Данни!$A:$A,0))) -> 56 | G12: =F12-E12 -> -2.03 | H12: =IF(E12=0,0,G12/E12) -> -0.034981906 | I12: =IF(H12>=0.5,"🚀 Отлично!",IF(H12>=0.2,"✅ Добре",IF(H12>=0,"📈 На плюс",IF(H12>=-0.15,"😐 Малка загуба — задръж",IF(H12>=-0.3,"⚠️ Внимание","🚨 Под -30% — прегледай стратегия"))))) -> 😐 Малка загуба — задръж | J12: =IFERROR(INDEX(Live!$D:$D,MATCH($D12,Live!$A:$A,0)),INDEX(Данни!$D:$D,MATCH($D12,Данни!$A:$A,0))) -> 9.477678 | K12: =IFERROR(INDEX(Live!$E:$E,MATCH($D12,Live!$A:$A,0)),INDEX(Данни!$E:$E,MATCH($D12,Данни!$A:$A,0))) -> USD | L12: =IFERROR(IFERROR(INDEX(Live!$L:$L,MATCH($D12,Live!$A:$A,0)),INDEX(Данни!$L:$L,MATCH($D12,Данни!$A:$A,0)))/100,0) -> 0
C13: Flare | D13: FLR | E13: =IFERROR(INDEX(Live!$I:$I,MATCH($D13,Live!$A:$A,0)),INDEX(Данни!$I:$I,MATCH($D13,Данни!$A:$A,0))) -> 0.1 | F13: =IFERROR(INDEX(Live!$H:$H,MATCH($D13,Live!$A:$A,0)),INDEX(Данни!$H:$H,MATCH($D13,Данни!$A:$A,0))) -> 0.09 | G13: =F13-E13 -> -0.01 | H13: =IF(E13=0,0,G13/E13) -> -0.1 | I13: =IF(H13>=0.5,"🚀 Отлично!",IF(H13>=0.2,"✅ Добре",IF(H13>=0,"📈 На плюс",IF(H13>=-0.15,"😐 Малка загуба — задръж",IF(H13>=-0.3,"⚠️ Внимание","🚨 Под -30% — прегледай стратегия"))))) -> 😐 Малка загуба — задръж | J13: =IFERROR(INDEX(Live!$D:$D,MATCH($D13,Live!$A:$A,0)),INDEX(Данни!$D:$D,MATCH($D13,Данни!$A:$A,0))) -> 0.00692 | K13: =IFERROR(INDEX(Live!$E:$E,MATCH($D13,Live!$A:$A,0)),INDEX(Данни!$E:$E,MATCH($D13,Данни!$A:$A,0))) -> USD | L13: =IFERROR(IFERROR(INDEX(Live!$L:$L,MATCH($D13,Live!$A:$A,0)),INDEX(Данни!$L:$L,MATCH($D13,Данни!$A:$A,0)))/100,0) -> 0
C14: ОБЩО ПОРТФОЛИО | E14: =SUM(E6:E13) -> 398.67 | F14: =SUM(F6:F13) -> 428.16 | G14: =F14-E14 -> 29.49 | H14: =IF(E14=0,0,G14/E14) -> 0.073970953 | I14: =IF(H14>=0,"📈 Портфейлът е на плюс","📉 Портфейлът е на минус") -> 📈 Портфейлът е на плюс
B16: КЕШ (извън P&L)
C17: Personal | D17: PERSONAL | F17: =IFERROR(INDEX(Live!$H:$H,MATCH($D17,Live!$A:$A,0)),INDEX(Данни!$H:$H,MATCH($D17,Данни!$A:$A,0))) -> 126.76
C18: Cash balance | D18: CASH | F18: =IFERROR(INDEX(Live!$H:$H,MATCH($D18,Live!$A:$A,0)),INDEX(Данни!$H:$H,MATCH($D18,Данни!$A:$A,0))) -> 0.43
C19: ОБЩО С КЕШ | F19: =F14+SUM(F17:F18) -> 555.35
B22: 💸 КОГА ДА ТЕГЛИШ — УМНИЯТ КАЛКУЛАТОР
B23: Жълто = въвеждаш ти; всичко останало се смята само.
B24: Искам да изтегля (€): | E24: 0 | F24: Сумата, която искаш да изтеглиш
B25: Обща текуща стойност (€): | E25: =F14 -> 428.16 | F25: Автоматично от таблицата горе
B26: Общо вложено (€): | E26: =E14 -> 398.67 | F26: Автоматично от таблицата горе
B27: Доходност на портфейла: | E27: =H14 -> 0.073970953
B28: След теглене остава (€): | E28: =E25-E24 -> 428.16
B29: % от портфолиото изтеглено: | E29: =IF(E25=0,0,E24/E25) -> 0
B31: Сигнал: | C31: =IF(E24=0,"Въведи сума за теглене в жълтото поле",IF(OR(E27<0,E29>0.5),"🔴 ЧЕРВЕНА СВЕТЛИНА — не теглиш",IF(AND(E27>0.2,E29<0.25),"🟢 ЗЕЛЕНА СВЕТЛИНА — може, ако имаш конкретна нужда","🟡 ЖЪЛТА СВЕТЛИНА — помисли, може би изчакай"))) -> Въведи сума за теглене в жълтото поле
B33: 📋 ПРАВИЛА ЗА ТЕГЛЕНЕ — Твоят дългосрочен план
B34: 🟢 ЗЕЛЕНА СВЕТЛИНА | D34: Теглиш ако: На печалба над +20% И тегленето е под 25% от портфолиото И имаш конкретна нужда (спешно)
B35: 🟡 ЖЪЛТА СВЕТЛИНА | D35: Помисли ако: На малка печалба (0-20%) ИЛИ тегленето е 25-50% от портфолиото — може би изчакай
B36: 🔴 ЧЕРВЕНА СВЕТЛИНА | D36: НЕ теглиш ако: На загуба ИЛИ тегленето е над 50% ИЛИ нямаш конкретна причина — емоциите лъжат
B37: 💡 ЗЛАТНОТО ПРАВИЛО | D37: Никога не тегли от паника. Ако пазарът падна — точно тогава НЕ продавай. Изчакай възстановяване.
B38: ⏰ ВРЕМЕВИ ХОРИЗОНТ | D38: Ако не ти трябват парите следващите 12 месеца — не теглиш. Времето е твой най-добър съюзник.
B40: 📖 ИСТОРИЯ НА ТЕГЛЕНИЯТА
B41: Дата | C41: Актив | E41: Сума изтеглена (€) | F41: Цена при теглене | G41: Бележка
B42: пример → | C42: (напр. BTC)
B54: Общо изтеглено: | E54: =SUM(E42:E53) -> 0

Sheet Live

Sheet История

Sheet Данни
A1: asset | B1: name | C1: group | D1: price | E1: ccy | F1: price_eur | G1: qty | H1: value_eur | I1: invested_eur | J1: pnl_eur | K1: pnl_pct | L1: chg_day_pct | M1: updated | N1: src
A2: BTC | B2: Bitcoin | C2: crypto | D2: 84835.06 | E2: USD | F2: 74514.765 | G2: 0.00162035 | H2: 120.74 | I2: 107 | J2: 13.74 | K2: 12.84 | M2: 2026-09-27T14:34+03:00 | N2: revolut
A3: ETC | B3: Ethereum Classic | C3: crypto | D3: 9.477678 | E3: USD | F3: 8.324706 | G3: 6.7269645 | H3: 56 | I3: 58.03 | J3: -2.03 | K3: -3.5 | M3: 2026-09-27T14:34+03:00 | N3: revolut
A4: FLR | B4: Flare | C4: crypto | D4: 0.00692 | E4: USD | F4: 0.006078 | G4: 14.808014 | H4: 0.09 | I4: 0.1 | J4: -0.01 | K4: -10 | M4: 2026-09-27T14:34+03:00 | N4: revolut
A5: EXI2 | B5: iShares ETF (EXI2) | C5: stocks | D5: 117.70528 | E5: EUR | F5: 117.70528 | G5: 0.47746371 | H5: 56.2 | I5: 50 | J5: 6.2 | K5: 12.4 | M5: 2026-09-27T14:34+03:00 | N5: revolut
A6: MRVL | B6: Marvell | C6: stocks | D6: 261.77738 | E6: USD | F6: 229.93182 | G6: 0.2585984 | H6: 59.46 | I6: 37.04 | J6: 22.42 | K6: 60.53 | M6: 2026-09-27T14:34+03:00 | N6: revolut
A7: DFEN | B7: VanEck Defense ETF | C7: stocks | D7: 52.138653 | E7: EUR | F7: 52.138653 | G7: 0.87344028 | H7: 45.54 | I7: 49 | J7: -3.46 | K7: -7.06 | M7: 2026-09-27T14:34+03:00 | N7: revolut
A8: NVDA | B8: NVIDIA | C8: stocks | D8: 224.33783 | E8: USD | F8: 197.04684 | G8: 0.35179452 | H8: 69.32 | I8: 74.08 | J8: -4.76 | K8: -6.43 | M8: 2026-09-27T14:34+03:00 | N8: revolut
A9: ROBO | B9: Robo-Advisor | C9: stocks | D9: 20.81 | E9: EUR | F9: 20.81 | G9: 1 | H9: 20.81 | I9: 23.42 | J9: -2.61 | K9: -11.14 | M9: 2026-09-27T14:34+03:00 | N9: revolut
A10: PERSONAL | B10: Personal | C10: cash | D10: 126.76 | E10: EUR | F10: 126.76 | G10: 1 | H10: 126.76 | M10: 2026-09-27T14:34+03:00 | N10: revolut
A11: CASH | B11: Cash balance | C11: cash | D11: 0.43 | E11: EUR | F11: 0.43 | G11: 1 | H11: 0.43 | M11: 2026-09-27T14:34+03:00 | N11: revolut
A13: Снимка на latest.csv към 27.09.2026 (стойностите от Revolut). Ползва се само ако лист Live е празен.

Sheet Настройка
A1: ⚙️ ЕДНОКРАТНА НАСТРОЙКА — свързване с цените от бота (≈3 мин)
A3: Ботът записва цените всеки час в GitHub. Тази книга ги чете оттам чрез Power Query. След настройката: Data → Refresh All (Ctrl+Alt+F5).
A4: Докато не свържеш, лист „Портфейл“ показва снимката от лист „Данни“ (стойностите от Revolut към 27.09.2026).
A6: ЗАЯВКА 1 — текущи цени → лист Live
A7: 1. Data → Get Data → From Other Sources → Blank Query
A8: 2. В Power Query: Home → Advanced Editor → изтрий всичко и постави кода отдолу → Done
A9: 3. Вдясно Name: latest
A10: 4. Home → Close & Load ▾ → Close & Load To… → Table → Existing worksheet → =Live!$A$1 → OK
A11: КОД →
A12: let Source = Csv.Document(Web.Contents("https://raw.githubusercontent.com/asparuhtah/bot/main/docs/invest/latest.csv"), [Delimiter=",", Encoding=65001, QuoteStyle=QuoteStyle.Csv]), Headers = Table.PromoteHeaders(Source, [PromoteAllScalars=true]), Typed = Table.TransformColumnTypes(Headers, {{"price", type number}, {"price_eur", type number}, {"qty", type number}, {"value_eur", type number}, {"invested_eur", type number}, {"pnl_eur", type number}, {"pnl_pct", type number}, {"chg_day_pct", type number}}, "en-US") in Typed
A14: ЗАЯВКА 2 — дневна история → лист История (за графиката)
A15: Същите стъпки, Name: daily, Existing worksheet → =История!$A$1
... A23: Източници на файловете: https://raw.githubusercontent.com/asparuhtah/bot/main/docs/invest/latest.csv · https://raw.githubusercontent.com/asparuhtah/bot/main/docs/invest/daily.csv · https://raw.githubusercontent.com/asparuhtah/bot/main/docs/invest/prices_hourly.csv
